DataEase/__init__.py
DataEase/cleaner.py
DataEase/converter.py
DataEase/mysql_utils.py
DataEase/query_builder.py
DataEase/sql_utils.py
dataease-0.1.0.dist-info/licenses/LICENSE
tests/__init__.py
tests/test_cleaner.py
tests/test_converter.py
tests/test_mysql_utils.py
tests/test_query_builder.py
tests/test_sql_utils.py
dataease-0.1.0.dist-info/METADATA
dataease-0.1.0.dist-info/WHEEL
dataease-0.1.0.dist-info/top_level.txt
dataease-0.1.0.dist-info/RECORD
