Metadata-Version: 2.4
Name: DataEase
Version: 0.1.0
Summary: Simplify DataFrame cleaning, conversion, and MySQL interactions
Home-page: https://github.com/Praveen-A1012/DataEase
Author: Praveen Anand
Author-email: Praveen Anand <apraveen1012@gmail.com>
License: MIT
Project-URL: Homepage, https://github.com/Praveen-A1012/DataEase
Requires-Python: >=3.7
License-File: LICENSE
Requires-Dist: pandas
Requires-Dist: sqlalchemy
Requires-Dist: pymysql
Dynamic: author
Dynamic: home-page
Dynamic: license-file
Dynamic: requires-python
